calc/__init__.py
calc/calc.py
calc/functions.py
calc/preview.py
openedx_calc-4.0.3.dist-info/licenses/LICENSE
symmath/__init__.py
symmath/formula.py
symmath/symmath_check.py
openedx_calc-4.0.3.dist-info/METADATA
openedx_calc-4.0.3.dist-info/WHEEL
openedx_calc-4.0.3.dist-info/top_level.txt
openedx_calc-4.0.3.dist-info/RECORD
