Metadata-Version: 2.4
Name: openedx-calc
Version: 4.0.3
Summary: A helper library for mathematical calculations and symbolic mathematics, used by Open edX.
Home-page: https://github.com/openedx/openedx-calc
Author: edX
Author-email: oscm@edx.org
License: AGPL 3.0
Keywords: edx
Classifier: Development Status :: 5 - Production/Stable
Classifier: Intended Audience :: Developers
Classifier: License :: OSI Approved :: GNU Affero General Public License v3 or later (AGPLv3+)
Classifier: Natural Language :: English
Classifier: Programming Language :: Python :: 3
Classifier: Programming Language :: Python :: 3.11
Classifier: Programming Language :: Python :: 3.12
Requires-Python: >=3.11
License-File: LICENSE
Requires-Dist: lxml
Requires-Dist: markupsafe
Requires-Dist: numpy
Requires-Dist: pyparsing
Requires-Dist: sympy
Dynamic: author
Dynamic: author-email
Dynamic: classifier
Dynamic: description
Dynamic: description-content-type
Dynamic: home-page
Dynamic: keywords
Dynamic: license
Dynamic: license-file
Dynamic: requires-dist
Dynamic: requires-python
Dynamic: summary
